aws_prototyping_sdk/awsui_react_ts_website/__init__.py
aws_prototyping_sdk/awsui_react_ts_website/py.typed
aws_prototyping_sdk/awsui_react_ts_website/_jsii/__init__.py
aws_prototyping_sdk/awsui_react_ts_website/_jsii/awsui-react-ts-website@0.3.14.jsii.tgz
aws_prototyping_sdk.awsui_react_ts_website-0.3.14.dist-info/LICENSE
aws_prototyping_sdk.awsui_react_ts_website-0.3.14.dist-info/METADATA
aws_prototyping_sdk.awsui_react_ts_website-0.3.14.dist-info/WHEEL
aws_prototyping_sdk.awsui_react_ts_website-0.3.14.dist-info/top_level.txt
aws_prototyping_sdk.awsui_react_ts_website-0.3.14.dist-info/RECORD
