Metadata-Version: 2.1
Name: aws-prototyping-sdk.awsui-react-ts-website
Version: 0.3.14
Summary: @aws-prototyping-sdk/awsui-react-ts-website
Home-page: https://github.com/aws/aws-prototyping-sdk
Author: AWS APJ COPE<apj-cope@amazon.com>
License: Apache-2.0
Project-URL: Source, https://github.com/aws/aws-prototyping-sdk
Platform: UNKNOWN
Classifier: Intended Audience :: Developers
Classifier: Operating System :: OS Independent
Classifier: Programming Language :: JavaScript
Classifier: Programming Language :: Python :: 3 :: Only
Classifier: Programming Language :: Python :: 3.7
Classifier: Programming Language :: Python :: 3.8
Classifier: Programming Language :: Python :: 3.9
Classifier: Programming Language :: Python :: 3.10
Classifier: Typing :: Typed
Classifier: Development Status :: 4 - Beta
Classifier: License :: OSI Approved
Requires-Python: ~=3.7
Requires-Dist: jsii (<2.0.0,>=1.62.0)
Requires-Dist: projen (<0.59.0,>=0.58.33)
Requires-Dist: publication (>=0.0.3)
